{
    "Symbol": "CSCO",
    "AssetType": "Common Stock",
    "Name": "Cisco Systems Inc",
    "Description": "Cisco Systems, Inc. is an American multinational technology conglomerate headquartered in San Jose, California, in the center of Silicon Valley. Cisco develops, manufactures and sells networking hardware, software, telecommunications equipment and other high-technology services and products. Through its numerous acquired subsidiaries, such as OpenDNS, Webex, Jabber and Jasper, Cisco specializes in specific tech markets, such as the Internet of Things (IoT), domain security and energy management. On January 25, 2021, Cisco reincorporated in Delaware.",
    "CIK": "858877",
    "Exchange": "NASDAQ",
    "Currency": "USD",
    "Country": "USA",
    "Sector": "TECHNOLOGY",
    "Industry": "COMPUTER COMMUNICATIONS EQUIPMENT",
    "Address": "170 WEST TASMAN DR, SAN JOSE, CA, US",
    "OfficialSite": "https://www.cisco.com",
    "FiscalYearEnd": "July",
    "LatestQuarter": "2024-07-31",
    "MarketCapitalization": "209553228000",
    "EBITDA": "15282000000",
    "PERatio": "20.67",
    "PEGRatio": "2.555",
    "BookValue": "11.34",
    "DividendPerShare": "1.58",
    "DividendYield": "0.0303",
    "EPS": "2.54",
    "RevenuePerShareTTM": "13.31",
    "ProfitMargin": "0.192",
    "OperatingMarginTTM": "0.2",
    "ReturnOnAssetsTTM": "0.0722",
    "ReturnOnEquityTTM": "0.23",
    "RevenueTTM": "53803000000",
    "GrossProfitTTM": "35753000000",
    "DilutedEPSTTM": "2.54",
    "QuarterlyEarningsGrowthYOY": "-0.439",
    "QuarterlyRevenueGrowthYOY": "-0.103",
    "AnalystTargetPrice": "54.72",
    "AnalystRatingStrongBuy": "5",
    "AnalystRatingBuy": "3",
    "AnalystRatingHold": "21",
    "AnalystRatingSell": "0",
    "AnalystRatingStrongSell": "0",
    "TrailingPE": "20.67",
    "ForwardPE": "14.81",
    "PriceToSalesRatioTTM": "3.895",
    "PriceToBookRatio": "4.631",
    "EVToRevenue": "4.156",
    "EVToEBITDA": "14.2",
    "Beta": "0.822",
    "52WeekHigh": "52.91",
    "52WeekLow": "44.16",
    "50DayMovingAverage": "49.62",
    "200DayMovingAverage": "48.81",
    "SharesOutstanding": "3990730000",
    "DividendDate": "2024-10-23",
    "ExDividendDate": "2024-10-02"
}